sgn_ts-0.5.0.dist-info/licenses/LICENSE
sgnts/__init__.py
sgnts/_version.py
sgnts/compose.py
sgnts/filtertools.py
sgnts/plotting.py
sgnts/utils.py
sgnts/base/__init__.py
sgnts/base/array_backend.py
sgnts/base/array_ops.py
sgnts/base/audioadapter.py
sgnts/base/base.py
sgnts/base/buffer.py
sgnts/base/notorch_backend.py
sgnts/base/numpy_backend.py
sgnts/base/offset.py
sgnts/base/slice_tools.py
sgnts/base/time.py
sgnts/base/torch_backend.py
sgnts/decorators/__init__.py
sgnts/decorators/sink.py
sgnts/decorators/transform.py
sgnts/sinks/__init__.py
sgnts/sinks/appsink.py
sgnts/sinks/collect.py
sgnts/sinks/dump.py
sgnts/sinks/null.py
sgnts/sinks/plot.py
sgnts/sources/__init__.py
sgnts/sources/fake_series.py
sgnts/sources/iter.py
sgnts/sources/segment.py
sgnts/transforms/__init__.py
sgnts/transforms/adder.py
sgnts/transforms/align.py
sgnts/transforms/amplify.py
sgnts/transforms/and_transform.py
sgnts/transforms/bit_gen.py
sgnts/transforms/converter.py
sgnts/transforms/correlate.py
sgnts/transforms/gate.py
sgnts/transforms/matmul.py
sgnts/transforms/nary.py
sgnts/transforms/resampler.py
sgnts/transforms/sumindex.py
sgnts/transforms/threshold.py
sgn_ts-0.5.0.dist-info/METADATA
sgn_ts-0.5.0.dist-info/WHEEL
sgn_ts-0.5.0.dist-info/entry_points.txt
sgn_ts-0.5.0.dist-info/top_level.txt
sgn_ts-0.5.0.dist-info/RECORD
