Metadata-Version: 2.4
Name: sgn-ts
Version: 0.5.0
Summary: TimeSeries Extensions for SGN Framework
Author-email: Chad Hanna <crh184@psu.edu>, Yun-Jing Huang <yzh5436@psu.edu>, James Kennington <jmk7376@psu.edu>
License: MPL-2.0
Project-URL: Homepage, https://git.ligo.org/greg/sgn-ts
Project-URL: Documentation, https://docs.ligo.org/greg/sgn-ts
Project-URL: Issues, https://git.ligo.org/greg/sgn-ts/issues
Classifier: Programming Language :: Python :: 3
Classifier: License :: OSI Approved :: Mozilla Public License 2.0 (MPL 2.0)
Classifier: Operating System :: OS Independent
Requires-Python: >=3.10
License-File: LICENSE
Requires-Dist: sgn>=0.5
Requires-Dist: numpy
Requires-Dist: scipy
Provides-Extra: torch
Requires-Dist: torch; extra == "torch"
Provides-Extra: plot
Requires-Dist: matplotlib; extra == "plot"
Provides-Extra: test
Requires-Dist: pytest; extra == "test"
Requires-Dist: pytest-cov; extra == "test"
Requires-Dist: sgn-ts[torch]; extra == "test"
Requires-Dist: sgn-ts[plot]; extra == "test"
Requires-Dist: pytest-markdown-docs; extra == "test"
Requires-Dist: gwpy; extra == "test"
Requires-Dist: gpstime; extra == "test"
Provides-Extra: docs
Requires-Dist: mkdocs; extra == "docs"
Requires-Dist: mkdocstrings; extra == "docs"
Requires-Dist: mkdocstrings-python; extra == "docs"
Requires-Dist: mkdocs-material; extra == "docs"
Requires-Dist: pymdown-extensions; extra == "docs"
Requires-Dist: sgn-ts[plot]; extra == "docs"
Provides-Extra: lint
Requires-Dist: black; extra == "lint"
Requires-Dist: flake8; extra == "lint"
Requires-Dist: flake8-bandit; extra == "lint"
Requires-Dist: flake8-black; extra == "lint"
Requires-Dist: flake8-bugbear; extra == "lint"
Requires-Dist: flake8-future-annotations; extra == "lint"
Requires-Dist: flake8-isort; extra == "lint"
Requires-Dist: flake8-logging-format; extra == "lint"
Requires-Dist: flake8-pyproject; extra == "lint"
Requires-Dist: isort; extra == "lint"
Requires-Dist: mypy; extra == "lint"
Requires-Dist: mypy-extensions; extra == "lint"
Provides-Extra: dev
Requires-Dist: sgn-ts[docs]; extra == "dev"
Requires-Dist: sgn-ts[lint]; extra == "dev"
Requires-Dist: sgn-ts[test]; extra == "dev"
Dynamic: license-file
